MANIFEST.in
setup.py
wappalyzer/__init__.py
wappalyzer/settings.py
wappalyzer/updater.py
wappalyzer/data/apps.json
wappalyzer/data/driver.js
wappalyzer/data/wappalyzer.js
wappalyzer/data/icons/1C-Bitrix.png
wappalyzer/data/icons/1und1.png
wappalyzer/data/icons/2z Project.png
wappalyzer/data/icons/3DM.png
wappalyzer/data/icons/3dCart.png
wappalyzer/data/icons/3ware.png
wappalyzer/data/icons/AMPcms.png
wappalyzer/data/icons/AOLserver.png
wappalyzer/data/icons/AT Internet Analyzer.png
wappalyzer/data/icons/AT Internet XiTi.png
wappalyzer/data/icons/ATEN.png
wappalyzer/data/icons/ATG Web Commerce.png
wappalyzer/data/icons/AWStats.png
wappalyzer/data/icons/Accessible Portal.png
wappalyzer/data/icons/AdInfinity.png
wappalyzer/data/icons/AdRiver.png
wappalyzer/data/icons/AdRoll.png
wappalyzer/data/icons/Adcash.png
wappalyzer/data/icons/AddShoppers.png
wappalyzer/data/icons/AddThis.png
wappalyzer/data/icons/Adobe CQ5.png
wappalyzer/data/icons/Adobe ColdFusion.png
wappalyzer/data/icons/Adobe GoLive.png
wappalyzer/data/icons/Adobe Muse.png
wappalyzer/data/icons/Adobe RoboHelp.png
wappalyzer/data/icons/Advanced Web Stats.png
wappalyzer/data/icons/Advert Stream.png
wappalyzer/data/icons/Adzerk.png
wappalyzer/data/icons/Airee.png
wappalyzer/data/icons/Akamai.png
wappalyzer/data/icons/Algolia Realtime Search.png
wappalyzer/data/icons/Allegro RomPager.png
wappalyzer/data/icons/Alloy.png
wappalyzer/data/icons/AlloyUI.png
wappalyzer/data/icons/Amaya.png
wappalyzer/data/icons/Ametys.png
wappalyzer/data/icons/Amiro.CMS.png
wappalyzer/data/icons/Anchor CMS.png
wappalyzer/data/icons/AngularJS.png
wappalyzer/data/icons/Apache HBase.png
wappalyzer/data/icons/Apache Hadoop.png
wappalyzer/data/icons/Apache JSPWiki.png
wappalyzer/data/icons/Apache Tomcat.png
wappalyzer/data/icons/Apache Traffic Server.png
wappalyzer/data/icons/Apache Wicket.png
wappalyzer/data/icons/Apache.png
wappalyzer/data/icons/AppNexus.png
wappalyzer/data/icons/Arc Forum.png
wappalyzer_python.egg-info/PKG-INFO
wappalyzer_python.egg-info/SOURCES.txt
wappalyzer_python.egg-info/dependency_links.txt
wappalyzer_python.egg-info/requires.txt
wappalyzer_python.egg-info/top_level.txt