Metadata-Version: 1.1
Name: wappalyzer-python
Version: 0.1.2
Summary: Python wrapper for Wappalyzer (utility that uncovers the technologies used on websites)
Home-page: https://github.com/gatufo/wappalyzer-python
Author: Javier Casas
Author-email: gatufo@gmail.com
License: UNKNOWN
Keywords: wappalyzer,scraping,crawling,site
Platform: UNKNOWN
Classifier: Development Status :: 4 - Beta
Classifier: Intended Audience :: Developers
Classifier: License :: OSI Approved :: GNU General Public License v3 (GPLv3)
Classifier: Operating System :: OS Independent
Classifier: Programming Language :: Python :: 2.7
Classifier: Topic :: Internet :: WWW/HTTP
